mackerel/__init__.py
mackerel/api.py
mackerel.api-1.0.2.dist-info/LICENSE.txt
mackerel.api-1.0.2.dist-info/METADATA
mackerel.api-1.0.2.dist-info/WHEEL
mackerel.api-1.0.2.dist-info/top_level.txt
mackerel.api-1.0.2.dist-info/RECORD
