Metadata-Version: 2.1
Name: mackerel.api
Version: 1.0.2
Summary: mackerel.api is a python client library for mackerel api         on Python 3.7 and above.
Home-page: https://github.com/10mohi6/mackerel-api-client-python
Author: 10mohi6
Author-email: 10.mohi.6.y@gmail.com
License: MIT
Keywords: mackerel rest api rest-api python client
Platform: UNKNOWN
Classifier: Development Status :: 5 - Production/Stable
Classifier: Programming Language :: Python
Classifier: Programming Language :: Python :: 3
Classifier: Programming Language :: Python :: 3.7
Classifier: Programming Language :: Python :: 3.8
Classifier: Programming Language :: Python :: 3.9
Classifier: Operating System :: OS Independent
Classifier: Intended Audience :: Developers
Classifier: Topic :: System :: Networking
Classifier: Topic :: Office/Business
Classifier: License :: OSI Approved :: MIT License
Requires-Python: >=3.7.0
License-File: LICENSE.txt
Requires-Dist: requests
